odoo/addons/event_phone/__init__.py
odoo/addons/event_phone/__manifest__.py
odoo/addons/event_phone/i18n/es.po
odoo/addons/event_phone/i18n/event_phone.pot
odoo/addons/event_phone/i18n/tr.po
odoo/addons/event_phone/models/__init__.py
odoo/addons/event_phone/models/event_registration.py
odoo/addons/event_phone/security/ir.model.access.csv
odoo/addons/event_phone/static/description/icon.png
odoo/addons/event_phone/views/hr_registration.xml
odoo11_addon_event_phone-11.0.1.0.0.99.dev5.dist-info/METADATA
odoo11_addon_event_phone-11.0.1.0.0.99.dev5.dist-info/RECORD
odoo11_addon_event_phone-11.0.1.0.0.99.dev5.dist-info/WHEEL
odoo11_addon_event_phone-11.0.1.0.0.99.dev5.dist-info/top_level.txt
